cdktf_gitlab_runner/__init__.py
cdktf_gitlab_runner/py.typed
cdktf_gitlab_runner/_jsii/__init__.py
cdktf_gitlab_runner/_jsii/cdktf-gitlab-runner@0.0.1442.jsii.tgz
cdktf_gitlab_runner-0.0.1442.dist-info/LICENSE
cdktf_gitlab_runner-0.0.1442.dist-info/METADATA
cdktf_gitlab_runner-0.0.1442.dist-info/WHEEL
cdktf_gitlab_runner-0.0.1442.dist-info/top_level.txt
cdktf_gitlab_runner-0.0.1442.dist-info/RECORD
