Metadata-Version: 2.1
Name: cdktf-gitlab-runner
Version: 0.0.1442
Summary: The CDK for Terraform Construct for Gitlab Runner on GCP
Home-page: https://github.com/neilkuan/cdktf-gitlab-runner.git
Author: Neil Kuan<guan840912@gmail.com>
License: Apache-2.0
Project-URL: Source, https://github.com/neilkuan/cdktf-gitlab-runner.git
Classifier: Intended Audience :: Developers
Classifier: Operating System :: OS Independent
Classifier: Programming Language :: JavaScript
Classifier: Programming Language :: Python :: 3 :: Only
Classifier: Programming Language :: Python :: 3.9
Classifier: Programming Language :: Python :: 3.10
Classifier: Programming Language :: Python :: 3.11
Classifier: Typing :: Typed
Classifier: Development Status :: 5 - Production/Stable
Classifier: License :: OSI Approved
Requires-Python: ~=3.9
License-File: LICENSE
Requires-Dist: cdktf-cdktf-provider-google <14.0.0,>=13.0.0
Requires-Dist: cdktf <0.21.0,>=0.20.0
Requires-Dist: constructs <11.0.0,>=10.3.0
Requires-Dist: jsii <2.0.0,>=1.119.0
Requires-Dist: publication >=0.0.3
Requires-Dist: typeguard <4.3.0,>=2.13.3
